{"nodes": [{"id": "d_cursor_new_client_src_setup_test_js", "label": "setup.test.js", "file_type": "code", "source_file": "D:\\Cursor_new\\client\\src\\setup.test.js", "source_location": "L1"}, {"id": "src_setup_test_localstoragemock", "label": "localStorageMock", "file_type": "code", "source_file": "D:\\Cursor_new\\client\\src\\setup.test.js", "source_location": "L12"}], "edges": [{"source": "d_cursor_new_client_src_setup_test_js", "target": "jest_dom", "relation": "imports_from", "context": "import", "confidence": "EXTRACTED", "source_file": "D:\\Cursor_new\\client\\src\\setup.test.js", "source_location": "L1", "weight": 1.0}, {"source": "d_cursor_new_client_src_setup_test_js", "target": "vitest", "relation": "imports_from", "context": "import", "confidence": "EXTRACTED", "source_file": "D:\\Cursor_new\\client\\src\\setup.test.js", "source_location": "L2", "weight": 1.0}, {"source": "d_cursor_new_client_src_setup_test_js", "target": "react", "relation": "imports_from", "context": "import", "confidence": "EXTRACTED", "source_file": "D:\\Cursor_new\\client\\src\\setup.test.js", "source_location": "L3", "weight": 1.0}, {"source": "d_cursor_new_client_src_setup_test_js", "target": "src_setup_test_localstoragemock", "relation": "contains", "confidence": "EXTRACTED", "source_file": "D:\\Cursor_new\\client\\src\\setup.test.js", "source_location": "L12", "weight": 1.0}], "raw_calls": []}